README.md
setup.cfg
setup.py
distributions/Binomialdistribution.py
distributions/Gaussiandistribution.py
distributions/Generaldistribution.py
distributions/__init__.py
ksb_distributions.egg-info/PKG-INFO
ksb_distributions.egg-info/SOURCES.txt
ksb_distributions.egg-info/dependency_links.txt
ksb_distributions.egg-info/not-zip-safe
ksb_distributions.egg-info/top_level.txt